[
    {
        "OrderItemID": "73fe9e15-2238-4689-8c43-11353a045ab7",
        "ProductName": "Muffin Mix - Carrot",
        "Quantity": 7,
        "UnitPrice": 2,
        "TotalPrice": 14,
        "OrderID": "538b01e3-4803-4e4a-9f3c-8ffdfa6092ab"
    },
    {
        "OrderItemID": "86d99f15-4445-495d-9064-f4422caf8f7e",
        "ProductName": "Myers Planters Punch",
        "Quantity": 2,
        "UnitPrice": 150,
        "TotalPrice": 300,
        "OrderID": "e6f372d0-a5f5-42b0-b3a8-71726f489f51"
    },
    {
        "OrderItemID": "10fcaeeb-9d0b-4078-be2e-224f08b1a62e",
        "ProductName": "Syrup - Kahlua Chocolate",
        "Quantity": 9,
        "UnitPrice": 10,
        "TotalPrice": 90,
        "OrderID": "e6f372d0-a5f5-42b0-b3a8-71726f489f51"
    },
    {
        "OrderItemID": "80352826-a906-4ed7-b131-2a078cb102e6",
        "ProductName": "Pork - Ham Hocks - Smoked",
        "Quantity": 8,
        "UnitPrice": 35.20,
        "TotalPrice": 281.60,
        "OrderID": "c5cebf9d-8ca1-4f41-b85d-b2120f452245"
    },
    {
        "OrderItemID": "7dfa2b06-62ae-4859-9b31-8bd328cc631f",
        "ProductName": "Water - Spring 1.5lit",
        "Quantity": 10,
        "UnitPrice": 2.50,
        "TotalPrice": 25,
        "OrderID": "c5cebf9d-8ca1-4f41-b85d-b2120f452245"
    },
    {
        "OrderItemID": "1de377e6-aced-4991-9ca5-3159a50089a5",
        "ProductName": "Pepper - Cayenne",
        "Quantity": 7,
        "UnitPrice": 8.90,
        "TotalPrice": 62.30,
        "OrderID": "4a62dddc-8fdd-4aeb-96f5-a03311348293"
    },
    {
        "OrderItemID": "f7f7814a-99bf-4ec8-a773-0115654bc2f4",
        "ProductName": "Tart Shells - Barquettes, Savory",
        "Quantity": 4,
        "UnitPrice": 169.50,
        "TotalPrice": 678,
        "OrderID": "4a62dddc-8fdd-4aeb-96f5-a03311348293"
    },
    {
        "OrderItemID": "88a37dbf-4c80-4aa2-aaa7-805ee8efd8e1",
        "ProductName": "Salmon - Atlantic, Fresh, Whole",
        "Quantity": 1,
        "UnitPrice": 175,
        "TotalPrice": 175,
        "OrderID": "4a62dddc-8fdd-4aeb-96f5-a03311348293"
    },
    {
        "OrderItemID": "b9bc4cde-9793-4ccd-b305-832cde69e720",
        "ProductName": "Snapple - Mango Maddness",
        "Quantity": 3,
        "UnitPrice": 57.70,
        "TotalPrice": 173.10,
        "OrderID": "4a62dddc-8fdd-4aeb-96f5-a03311348293"
    },
    {
        "OrderItemID": "53f45ce3-08e5-4b30-bbf6-0ed736bcee80",
        "ProductName": "Blackberries",
        "Quantity": 3,
        "UnitPrice": 26.90,
        "TotalPrice": 80.70,
        "OrderID": "7ad6b3ae-d67c-46f4-9561-f4cd129eca98"
    },
    {
        "OrderItemID": "ceccc0f2-bbbc-47e0-ab96-17985290786d",
        "ProductName": "Truffle Cups - Red",
        "Quantity": 8,
        "UnitPrice": 36.20,
        "TotalPrice": 289.60,
        "OrderID": "7ad6b3ae-d67c-46f4-9561-f4cd129eca98"
    },
    {
        "OrderItemID": "98ec3b95-7c84-4cc6-ac48-41c3ec15edba",
        "ProductName": "Potatoes - Idaho 80 Count",
        "Quantity": 18,
        "UnitPrice": 7.70,
        "TotalPrice": 138.60,
        "OrderID": "7ad6b3ae-d67c-46f4-9561-f4cd129eca98"
    },
    {
        "OrderItemID": "f31e87ab-aae4-40f0-8737-b0ed00d305f4",
        "ProductName": "Cheese - Cream Cheese",
        "Quantity": 4,
        "UnitPrice": 12.90,
        "TotalPrice": 51.60,
        "OrderID": "7ad6b3ae-d67c-46f4-9561-f4cd129eca98"
    },
    {
        "OrderItemID": "b8392c5d-65a4-4e9a-b74a-c202b996b19b",
        "ProductName": "Cheese - Havarti, Roasted Garlic",
        "Quantity": 2,
        "UnitPrice": 38.60,
        "TotalPrice": 77.20,
        "OrderID": "7ad6b3ae-d67c-46f4-9561-f4cd129eca98"
    },
    {
        "OrderItemID": "b6e117b2-da67-4e58-8cb3-6346b728823b",
        "ProductName": "Sprite - 355 Ml",
        "Quantity": 24,
        "UnitPrice": 1.70,
        "TotalPrice": 40.80,
        "OrderID": "1be791b6-7578-4d2d-92b8-b4c9d5300dc1"
    },
    {
        "OrderItemID": "67e8f4f0-f086-43b5-9d62-15e67a04292f",
        "ProductName": "Veal - Inside",
        "Quantity": 9,
        "UnitPrice": 65,
        "TotalPrice": 585,
        "OrderID": "91f3d4de-2ae6-45ec-8f46-1966407403bd"
    },
    {
        "OrderItemID": "12da5931-6b2d-40f5-8eb0-c6b568c07a7b",
        "ProductName": "Beef - Ground Lean Fresh",
        "Quantity": 4,
        "UnitPrice": 73,
        "TotalPrice": 292,
        "OrderID": "91f3d4de-2ae6-45ec-8f46-1966407403bd"
    },
    {
        "OrderItemID": "58925077-d01c-4aaf-a4f8-bd574ab5f25e",
        "ProductName": "Beef Striploin Aaa",
        "Quantity": 4,
        "UnitPrice": 80,
        "TotalPrice": 320,
        "OrderID": "91f3d4de-2ae6-45ec-8f46-1966407403bd"
    },
    {
        "OrderItemID": "5170af9a-9eb9-4a11-99ce-0d346dc1fdef",
        "ProductName": "Gelatine Leaves - Envelopes",
        "Quantity": 7,
        "UnitPrice": 13.50,
        "TotalPrice": 94.50,
        "OrderID": "a16409c9-d498-4469-b8f5-5b7348fb7034"
    },
    {
        "OrderItemID": "96f4866a-25c1-4a17-bbcb-96823976d1d3",
        "ProductName": "Rabbit - Frozen",
        "Quantity": 2,
        "UnitPrice": 37,
        "TotalPrice": 74,
        "OrderID": "f8a55368-f4f4-4ce8-a26e-4139fa9fa6bb"
    },
    {
        "OrderItemID": "2aec3fc0-7ba2-4fb7-ad4c-609445e06eb1",
        "ProductName": "Puree - Raspberry",
        "Quantity": 4,
        "UnitPrice": 87,
        "TotalPrice": 348,
        "OrderID": "f8a55368-f4f4-4ce8-a26e-4139fa9fa6bb"
    },
    {
        "OrderItemID": "2c809175-0472-4559-8e94-7b78bd4de652",
        "ProductName": "Wine - Masi Valpolocell",
        "Quantity": 5,
        "UnitPrice": 278,
        "TotalPrice": 1390,
        "OrderID": "f8a55368-f4f4-4ce8-a26e-4139fa9fa6bb"
    }
]